[
  {
    "description": "    Como usuário, desejo realizar um Cadastro\n    Para que possa acessar o sistema ",
    "keyword": "Funcionalidade",
    "name": "Cadastro",
    "line": 2,
    "id": "cadastro",
    "tags": [],
    "uri": "Cadastro.feature",
    "elements": [
      {
        "id": "cadastro;cadastro-de-usuário-no-site",
        "keyword": "Scenario",
        "line": 7,
        "name": "Cadastro de usuário no site",
        "tags": [],
        "type": "scenario",
        "steps": [
          {
            "arguments": [],
            "keyword": "Dado ",
            "line": 9,
            "name": "que acesso o site",
            "result": {
              "status": "passed",
              "duration": 11110000000
            }
          },
          {
            "arguments": [],
            "keyword": "Quando ",
            "line": 10,
            "name": "informar meus dados",
            "result": {
              "status": "passed",
              "duration": 4986000000
            }
          },
          {
            "arguments": [],
            "keyword": "E ",
            "line": 11,
            "name": "salvar",
            "result": {
              "status": "passed",
              "duration": 258000000
            }
          },
          {
            "arguments": [],
            "keyword": "Entao ",
            "line": 12,
            "name": "devo ser cadastrado com sucesso",
            "result": {
              "status": "passed",
              "duration": 11080000000
            }
          }
        ]
      }
    ]
  },
  {
    "description": "    Como usuário, desejo acessar a listagem \n    Para que possa visualizar meus dados de cadastro",
    "keyword": "Feature",
    "name": "Listagem",
    "line": 1,
    "id": "listagem",
    "tags": [],
    "uri": "Listagem.feature",
    "elements": [
      {
        "id": "listagem;listagem-sem-registros",
        "keyword": "Scenario",
        "line": 6,
        "name": "Listagem sem registros",
        "tags": [],
        "type": "scenario",
        "steps": [
          {
            "arguments": [],
            "keyword": "Given ",
            "line": 7,
            "name": "que o site não possui registros",
            "result": {
              "status": "passed",
              "duration": 28405000000
            }
          },
          {
            "arguments": [],
            "keyword": "When ",
            "line": 8,
            "name": "acessar a listagem",
            "result": {
              "status": "passed",
              "duration": 3149000000
            }
          },
          {
            "arguments": [],
            "keyword": "Then ",
            "line": 9,
            "name": "devo visualizar a lista vazia",
            "result": {
              "status": "passed",
              "duration": 48000000
            }
          }
        ]
      },
      {
        "id": "listagem;listagem-com-apenas-um-registro",
        "keyword": "Scenario",
        "line": 11,
        "name": "Listagem com apenas um registro",
        "tags": [],
        "type": "scenario",
        "steps": [
          {
            "arguments": [],
            "keyword": "Given ",
            "line": 12,
            "name": "que o site possui apenas um registros",
            "result": {
              "status": "passed",
              "duration": 169000000
            }
          },
          {
            "arguments": [],
            "keyword": "When ",
            "line": 13,
            "name": "acessar a listagem",
            "result": {
              "status": "passed",
              "duration": 2452000000
            }
          },
          {
            "arguments": [],
            "keyword": "Then ",
            "line": 14,
            "name": "devo visualizar apenas um registro",
            "result": {
              "status": "passed",
              "duration": 167000000
            }
          }
        ]
      }
    ]
  }
]
